{
"meta":{"test_sets":[],"test_metrics":[],"learn_metrics":[{"best_value":"Min","name":"Logloss"}],"launch_mode":"Train","parameters":"","iteration_count":500,"learn_sets":["learn"],"name":"experiment"},
"iterations":[
{"learn":[0.5987395612],"iteration":0,"passed_time":0.03642403844,"remaining_time":18.17559518},
{"learn":[0.5214145862],"iteration":1,"passed_time":0.06250366006,"remaining_time":15.56341136},
{"learn":[0.4515215899],"iteration":2,"passed_time":0.08952620931,"remaining_time":14.83150868},
{"learn":[0.3879046135],"iteration":3,"passed_time":0.1166735843,"remaining_time":14.46752446},
{"learn":[0.3313550569],"iteration":4,"passed_time":0.1437857007,"remaining_time":14.23478437},
{"learn":[0.2804870675],"iteration":5,"passed_time":0.1701246505,"remaining_time":14.00692956},
{"learn":[0.2375144321],"iteration":6,"passed_time":0.1962568619,"remaining_time":13.82209042},
{"learn":[0.2060669656],"iteration":7,"passed_time":0.2252489078,"remaining_time":13.85280783},
{"learn":[0.1771625855],"iteration":8,"passed_time":0.25239664,"remaining_time":13.76963892},
{"learn":[0.1524930925],"iteration":9,"passed_time":0.2782968762,"remaining_time":13.63654693},
{"learn":[0.1330578175],"iteration":10,"passed_time":0.3052902021,"remaining_time":13.57153716},
{"learn":[0.1167803096],"iteration":11,"passed_time":0.3321351232,"remaining_time":13.50682835},
{"learn":[0.1032413421],"iteration":12,"passed_time":0.3587800934,"remaining_time":13.44045427},
{"learn":[0.09131120849],"iteration":13,"passed_time":0.3860302335,"remaining_time":13.40076382},
{"learn":[0.08116140832],"iteration":14,"passed_time":0.4193428261,"remaining_time":13.55875138},
{"learn":[0.07256779887],"iteration":15,"passed_time":0.446078646,"remaining_time":13.49387904},
{"learn":[0.06499150079],"iteration":16,"passed_time":0.4725138955,"remaining_time":13.42495362},
{"learn":[0.05830371364],"iteration":17,"passed_time":0.4984998826,"remaining_time":13.34871908},
{"learn":[0.05313800875],"iteration":18,"passed_time":0.5245167425,"remaining_time":13.27855543},
{"learn":[0.04845928963],"iteration":19,"passed_time":0.5516494993,"remaining_time":13.23958798},
{"learn":[0.04424483143],"iteration":20,"passed_time":0.5769024095,"remaining_time":13.15886925},
{"learn":[0.04077968995],"iteration":21,"passed_time":0.60433381,"remaining_time":13.13052551},
{"learn":[0.03797639551],"iteration":22,"passed_time":0.6363833679,"remaining_time":13.19803767},
{"learn":[0.03534364593],"iteration":23,"passed_time":0.66111609,"remaining_time":13.11213579},
{"learn":[0.03292186896],"iteration":24,"passed_time":0.6873267978,"remaining_time":13.05920916},
{"learn":[0.03066087708],"iteration":25,"passed_time":0.7142399166,"remaining_time":13.0211431},
{"learn":[0.0289221589],"iteration":26,"passed_time":0.7404694351,"remaining_time":12.97192751},
{"learn":[0.02713173619],"iteration":27,"passed_time":0.7667402093,"remaining_time":12.92504924},
{"learn":[0.0254173576],"iteration":28,"passed_time":0.7935496231,"remaining_time":12.88834043},
{"learn":[0.02380687041],"iteration":29,"passed_time":0.8224743007,"remaining_time":12.88543071},
{"learn":[0.02271397808],"iteration":30,"passed_time":0.854185678,"remaining_time":12.92300268},
{"learn":[0.0218757669],"iteration":31,"passed_time":0.881953124,"remaining_time":12.89856444},
{"learn":[0.02101288271],"iteration":32,"passed_time":0.9099586303,"remaining_time":12.87729334},
{"learn":[0.02011482209],"iteration":33,"passed_time":0.9413052265,"remaining_time":12.90141869},
{"learn":[0.01935831317],"iteration":34,"passed_time":0.9714739034,"remaining_time":12.90672472},
{"learn":[0.01874234312],"iteration":35,"passed_time":0.9982050872,"remaining_time":12.86575446},
{"learn":[0.01816465313],"iteration":36,"passed_time":1.022748349,"remaining_time":12.79817529},
{"learn":[0.01759921445],"iteration":37,"passed_time":1.048892416,"remaining_time":12.75232358},
{"learn":[0.01710389764],"iteration":38,"passed_time":1.073316216,"remaining_time":12.68714809},
{"learn":[0.01643563476],"iteration":39,"passed_time":1.099431828,"remaining_time":12.64346603},
{"learn":[0.01589695502],"iteration":40,"passed_time":1.128451759,"remaining_time":12.63315506},
{"learn":[0.01549016638],"iteration":41,"passed_time":1.153067692,"remaining_time":12.57392864},
{"learn":[0.01497620234],"iteration":42,"passed_time":1.182098817,"remaining_time":12.56323626},
{"learn":[0.0145216665],"iteration":43,"passed_time":1.207267969,"remaining_time":12.51168622},
{"learn":[0.01421906251],"iteration":44,"passed_time":1.233112606,"remaining_time":12.46813857},
{"learn":[0.01390916447],"iteration":45,"passed_time":1.255580309,"remaining_time":12.39203175},
{"learn":[0.0135572749],"iteration":46,"passed_time":1.283817006,"remaining_time":12.37381072},
{"learn":[0.01330098837],"iteration":47,"passed_time":1.306742999,"remaining_time":12.30516324},
{"learn":[0.01308232262],"iteration":48,"passed_time":1.33109883,"remaining_time":12.25154229},
{"learn":[0.01280939995],"iteration":49,"passed_time":1.35927482,"remaining_time":12.23347338},
{"learn":[0.012531589],"iteration":50,"passed_time":1.384868542,"remaining_time":12.19227403},
{"learn":[0.01228926794],"iteration":51,"passed_time":1.412218036,"remaining_time":12.16680154},
{"learn":[0.01205187616],"iteration":52,"passed_time":1.438870631,"remaining_time":12.1353806},
{"learn":[0.01183397039],"iteration":53,"passed_time":1.465802682,"remaining_time":12.10644438},
{"learn":[0.01167155857],"iteration":54,"passed_time":1.490086867,"remaining_time":12.05615738},
{"learn":[0.01148532472],"iteration":55,"passed_time":1.521935033,"remaining_time":12.06677062},
{"learn":[0.01130850742],"iteration":56,"passed_time":1.552586494,"remaining_time":12.06659328},
{"learn":[0.01116419705],"iteration":57,"passed_time":1.582556689,"remaining_time":12.06017339},
{"learn":[0.01110435101],"iteration":58,"passed_time":1.61333921,"remaining_time":12.05902697},
{"learn":[0.01096716261],"iteration":59,"passed_time":1.644551736,"remaining_time":12.06004606},
{"learn":[0.01084292414],"iteration":60,"passed_time":1.67113149,"remaining_time":12.02666761},
{"learn":[0.01073339115],"iteration":61,"passed_time":1.697119654,"remaining_time":11.98932917},
{"learn":[0.01068213011],"iteration":62,"passed_time":1.723614166,"remaining_time":11.95586334},
{"learn":[0.01055210384],"iteration":63,"passed_time":1.750350196,"remaining_time":11.92426071},
{"learn":[0.01046224651],"iteration":64,"passed_time":1.776219624,"remaining_time":11.88700825},
{"learn":[0.01037495169],"iteration":65,"passed_time":1.801024616,"remaining_time":11.84310126},
{"learn":[0.01028200135],"iteration":66,"passed_time":1.8292945,"remaining_time":11.82215699},
{"learn":[0.01020841725],"iteration":67,"passed_time":1.854934473,"remaining_time":11.78428959},
{"learn":[0.0101193864],"iteration":68,"passed_time":1.880629198,"remaining_time":11.74711862},
{"learn":[0.01005354721],"iteration":69,"passed_time":1.908248047,"remaining_time":11.72209514},
{"learn":[0.00999621008],"iteration":70,"passed_time":1.932680211,"remaining_time":11.67774381},
{"learn":[0.009934922891],"iteration":71,"passed_time":1.958830113,"remaining_time":11.64415678},
{"learn":[0.009897373275],"iteration":72,"passed_time":1.986969932,"remaining_time":11.62241316},
{"learn":[0.009838095528],"iteration":73,"passed_time":2.012929652,"remaining_time":11.58794637},
{"learn":[0.009805224269],"iteration":74,"passed_time":2.041076077,"remaining_time":11.56609777},
{"learn":[0.009691326673],"iteration":75,"passed_time":2.067222339,"remaining_time":11.53292463},
{"learn":[0.009631882139],"iteration":76,"passed_time":2.093278886,"remaining_time":11.49944115},
{"learn":[0.009584474861],"iteration":77,"passed_time":2.12158909,"remaining_time":11.47834098},
{"learn":[0.009498681609],"iteration":78,"passed_time":2.147764623,"remaining_time":11.44568236},
{"learn":[0.009451866986],"iteration":79,"passed_time":2.173808801,"remaining_time":11.41249621},
{"learn":[0.009408272227],"iteration":80,"passed_time":2.199444576,"remaining_time":11.3773738},
{"learn":[0.009369853276],"iteration":81,"passed_time":2.226881468,"remaining_time":11.35166407},
{"learn":[0.009287753992],"iteration":82,"passed_time":2.253781294,"remaining_time":11.32321445},
{"learn":[0.009235464981],"iteration":83,"passed_time":2.279946405,"remaining_time":11.29116315},
{"learn":[0.009202325424],"iteration":84,"passed_time":2.306071082,"remaining_time":11.25905293},
{"learn":[0.009126549544],"iteration":85,"passed_time":2.334824602,"remaining_time":11.23973704},
{"learn":[0.009097814895],"iteration":86,"passed_time":2.36041695,"remaining_time":11.20519771},
{"learn":[0.009069108913],"iteration":87,"passed_time":2.387208897,"remaining_time":11.17647802},
{"learn":[0.009037999903],"iteration":88,"passed_time":2.413135354,"remaining_time":11.14380483},
{"learn":[0.0089975408],"iteration":89,"passed_time":2.441675968,"remaining_time":11.12319052},
{"learn":[0.008959810266],"iteration":90,"passed_time":2.468001931,"remaining_time":11.09244824},
{"learn":[0.008896663339],"iteration":91,"passed_time":2.492488034,"remaining_time":11.05364259},
{"learn":[0.008865350064],"iteration":92,"passed_time":2.518956994,"remaining_time":11.02382254},
{"learn":[0.008838812716],"iteration":93,"passed_time":2.545235011,"remaining_time":10.99324909},
{"learn":[0.008811498952],"iteration":94,"passed_time":2.570327544,"remaining_time":10.95771216},
{"learn":[0.008781222866],"iteration":95,"passed_time":2.596091923,"remaining_time":10.92522017},
{"learn":[0.008758560257],"iteration":96,"passed_time":2.622725948,"remaining_time":10.89647997},
{"learn":[0.008735056099],"iteration":97,"passed_time":2.645656988,"remaining_time":10.85259295},
{"learn":[0.008713234238],"iteration":98,"passed_time":2.672118634,"remaining_time":10.82343002},
{"learn":[0.00869367182],"iteration":99,"passed_time":2.697146697,"remaining_time":10.78858679},
{"learn":[0.008668217196],"iteration":100,"passed_time":2.729011779,"remaining_time":10.78094752},
{"learn":[0.008642611464],"iteration":101,"passed_time":2.760600048,"remaining_time":10.77175313},
{"learn":[0.008621495851],"iteration":102,"passed_time":2.791044943,"remaining_time":10.75771692},
{"learn":[0.008597402933],"iteration":103,"passed_time":2.821283974,"remaining_time":10.74258129},
{"learn":[0.008574329251],"iteration":104,"passed_time":2.853699744,"remaining_time":10.73534666},
{"learn":[0.008546406667],"iteration":105,"passed_time":2.881319173,"remaining_time":10.709809},
{"learn":[0.008523148781],"iteration":106,"passed_time":2.908061177,"remaining_time":10.68100974},
{"learn":[0.008501143197],"iteration":107,"passed_time":2.935383583,"remaining_time":10.65435523},
{"learn":[0.008451152722],"iteration":108,"passed_time":2.961753187,"remaining_time":10.62427061},
{"learn":[0.008439677323],"iteration":109,"passed_time":2.986530636,"remaining_time":10.58860862},
{"learn":[0.008424713525],"iteration":110,"passed_time":3.013171693,"remaining_time":10.55967377},
{"learn":[0.008406319283],"iteration":111,"passed_time":3.039292069,"remaining_time":10.5289761},
{"learn":[0.008384935458],"iteration":112,"passed_time":3.064551118,"remaining_time":10.49540958},
{"learn":[0.008352284992],"iteration":113,"passed_time":3.092125203,"remaining_time":10.46982744},
{"learn":[0.008326796667],"iteration":114,"passed_time":3.118481389,"remaining_time":10.44013334},
{"learn":[0.008310684433],"iteration":115,"passed_time":3.145396805,"remaining_time":10.41234804},
{"learn":[0.008293936178],"iteration":116,"passed_time":3.170508064,"remaining_time":10.3786717},
{"learn":[0.008278154503],"iteration":117,"passed_time":3.196338515,"remaining_time":10.34746875},
{"learn":[0.008258412392],"iteration":118,"passed_time":3.224899198,"remaining_time":10.32509743},
{"learn":[0.008243033187],"iteration":119,"passed_time":3.251217596,"remaining_time":10.29552239},
{"learn":[0.008228576811],"iteration":120,"passed_time":3.27888581,"remaining_time":10.27022911},
{"learn":[0.008199027317],"iteration":121,"passed_time":3.304237516,"remaining_time":10.23771952},
{"learn":[0.008156053015],"iteration":122,"passed_time":3.329963452,"remaining_time":10.20647335},
{"learn":[0.008144191251],"iteration":123,"passed_time":3.356032015,"remaining_time":10.17635514},
{"learn":[0.008135871584],"iteration":124,"passed_time":3.382304577,"remaining_time":10.14691373},
{"learn":[0.008125297049],"iteration":125,"passed_time":3.408056455,"remaining_time":10.1159771},
{"learn":[0.008097920641],"iteration":126,"passed_time":3.435194959,"remaining_time":10.08919464},
{"learn":[0.008072730499],"iteration":127,"passed_time":3.461452681,"remaining_time":10.05984685},
{"learn":[0.008059486108],"iteration":128,"passed_time":3.487440431,"remaining_time":10.02977054},
{"learn":[0.008042338452],"iteration":129,"passed_time":3.519679211,"remaining_time":10.01754852},
{"learn":[0.008021609002],"iteration":130,"passed_time":3.551352622,"remaining_time":10.00342838},
{"learn":[0.007999458088],"iteration":131,"passed_time":3.580975651,"remaining_time":9.983326057},
{"learn":[0.007982166003],"iteration":132,"passed_time":3.611878631,"remaining_time":9.966612463},
{"learn":[0.007969998919],"iteration":133,"passed_time":3.642236264,"remaining_time":9.948197558},
{"learn":[0.007959847254],"iteration":134,"passed_time":3.668147611,"remaining_time":9.917584282},
{"learn":[0.007936926244],"iteration":135,"passed_time":3.694025084,"remaining_time":9.88694949},
{"learn":[0.007926054369],"iteration":136,"passed_time":3.721326088,"remaining_time":9.860155985},
{"learn":[0.007915901622],"iteration":137,"passed_time":3.748083613,"remaining_time":9.831929478},
{"learn":[0.007894917981],"iteration":138,"passed_time":3.776263024,"remaining_time":9.807416918},
{"learn":[0.007875762127],"iteration":139,"passed_time":3.802006455,"remaining_time":9.776588027},
{"learn":[0.007860334659],"iteration":140,"passed_time":3.828513785,"remaining_time":9.747776233},
{"learn":[0.007825043401],"iteration":141,"passed_time":3.855660231,"remaining_time":9.720608188},
{"learn":[0.007812902672],"iteration":142,"passed_time":3.880933335,"remaining_time":9.68876364},
{"learn":[0.00779782881],"iteration":143,"passed_time":3.908634616,"remaining_time":9.663013355},
{"learn":[0.007782280083],"iteration":144,"passed_time":3.934018946,"remaining_time":9.631563627},
{"learn":[0.007767461434],"iteration":145,"passed_time":3.959601442,"remaining_time":9.600677469},
{"learn":[0.0077534656],"iteration":146,"passed_time":3.98741471,"remaining_time":9.575220358},
{"learn":[0.007748253947],"iteration":147,"passed_time":4.013460116,"remaining_time":9.545526764},
{"learn":[0.007729086839],"iteration":148,"passed_time":4.039352196,"remaining_time":9.515520946},
{"learn":[0.007715835768],"iteration":149,"passed_time":4.067320952,"remaining_time":9.490415554},
{"learn":[0.007703893989],"iteration":150,"passed_time":4.093758796,"remaining_time":9.461733905},
{"learn":[0.007668475133],"iteration":151,"passed_time":4.122400786,"remaining_time":9.438128115},
{"learn":[0.007649670116],"iteration":152,"passed_time":4.149517269,"remaining_time":9.410996683},
{"learn":[0.007620600959],"iteration":153,"passed_time":4.176198877,"remaining_time":9.382888385},
{"learn":[0.007592782424],"iteration":154,"passed_time":4.201220216,"remaining_time":9.351103062},
{"learn":[0.007581316111],"iteration":155,"passed_time":4.227860884,"remaining_time":9.322975282},
{"learn":[0.007554515426],"iteration":156,"passed_time":4.253843055,"remaining_time":9.29342782},
{"learn":[0.007536658813],"iteration":157,"passed_time":4.279894769,"remaining_time":9.26407602},
{"learn":[0.007526408757],"iteration":158,"passed_time":4.306968596,"remaining_time":9.236957807},
{"learn":[0.007508411147],"iteration":159,"passed_time":4.333400378,"remaining_time":9.208475802},
{"learn":[0.007498688192],"iteration":160,"passed_time":4.355770774,"remaining_time":9.171467655},
{"learn":[0.007491714225],"iteration":161,"passed_time":4.381724841,"remaining_time":9.14211726},
{"learn":[0.007478122606],"iteration":162,"passed_time":4.408294532,"remaining_time":9.114081332},
{"learn":[0.007469346971],"iteration":163,"passed_time":4.432969229,"remaining_time":9.082180859},
{"learn":[0.007457672081],"iteration":164,"passed_time":4.458087538,"remaining_time":9.051268638},
{"learn":[0.007446173454],"iteration":165,"passed_time":4.483679549,"remaining_time":9.021379333},
{"learn":[0.007438399361],"iteration":166,"passed_time":4.51001306,"remaining_time":8.993020054},
{"learn":[0.007428395251],"iteration":167,"passed_time":4.535718328,"remaining_time":8.963443362},
{"learn":[0.007417866813],"iteration":168,"passed_time":4.563687774,"remaining_time":8.93834706},
{"learn":[0.007411576168],"iteration":169,"passed_time":4.590703226,"remaining_time":8.911365086},
{"learn":[0.007403013625],"iteration":170,"passed_time":4.612604814,"remaining_time":8.874543764},
{"learn":[0.007387802075],"iteration":171,"passed_time":4.640277968,"remaining_time":8.848902171},
{"learn":[0.007378517697],"iteration":172,"passed_time":4.665981044,"remaining_time":8.819513304},
{"learn":[0.007367720443],"iteration":173,"passed_time":4.693751743,"remaining_time":8.794040621},
{"learn":[0.007361426608],"iteration":174,"passed_time":4.717938444,"remaining_time":8.761885681},
{"learn":[0.007348941963],"iteration":175,"passed_time":4.74384686,"remaining_time":8.732990811},
{"learn":[0.007341802087],"iteration":176,"passed_time":4.771301275,"remaining_time":8.706950914},
{"learn":[0.007334359274],"iteration":177,"passed_time":4.798322434,"remaining_time":8.68011137},
{"learn":[0.00731281718],"iteration":178,"passed_time":4.826336055,"remaining_time":8.655049573},
{"learn":[0.007299504126],"iteration":179,"passed_time":4.858101261,"remaining_time":8.636624463},
{"learn":[0.007292493632],"iteration":180,"passed_time":4.888418977,"remaining_time":8.61550085},
{"learn":[0.007288867186],"iteration":181,"passed_time":4.912970682,"remaining_time":8.584201521},
{"learn":[0.007279013283],"iteration":182,"passed_time":4.938790735,"remaining_time":8.555173022},
{"learn":[0.007271962049],"iteration":183,"passed_time":4.962043066,"remaining_time":8.521769613},
{"learn":[0.007265177824],"iteration":184,"passed_time":4.986766823,"remaining_time":8.490981348},
{"learn":[0.007257399098],"iteration":185,"passed_time":5.013227828,"remaining_time":8.463191065},
{"learn":[0.007250084042],"iteration":186,"passed_time":5.041610368,"remaining_time":8.438631257},
{"learn":[0.007240872419],"iteration":187,"passed_time":5.066994572,"remaining_time":8.409054821},
{"learn":[0.007234023082],"iteration":188,"passed_time":5.096038953,"remaining_time":8.385545578},
{"learn":[0.007209685302],"iteration":189,"passed_time":5.127388092,"remaining_time":8.365738466},
{"learn":[0.007205458581],"iteration":190,"passed_time":5.159112738,"remaining_time":8.34641799},
{"learn":[0.007191298822],"iteration":191,"passed_time":5.190947262,"remaining_time":8.327144567},
{"learn":[0.007183156501],"iteration":192,"passed_time":5.221240918,"remaining_time":8.305289957},
{"learn":[0.00717717493],"iteration":193,"passed_time":5.248876937,"remaining_time":8.279156406},
{"learn":[0.007171465123],"iteration":194,"passed_time":5.278563164,"remaining_time":8.25621418},
{"learn":[0.007163858626],"iteration":195,"passed_time":5.309939483,"remaining_time":8.235824505},
{"learn":[0.007145120405],"iteration":196,"passed_time":5.340182246,"remaining_time":8.213579799},
{"learn":[0.007125651685],"iteration":197,"passed_time":5.370166895,"remaining_time":8.190860618},
{"learn":[0.007119530562],"iteration":198,"passed_time":5.400056637,"remaining_time":8.167924863},
{"learn":[0.007113939666],"iteration":199,"passed_time":5.426201898,"remaining_time":8.139302848},
{"learn":[0.007107221998],"iteration":200,"passed_time":5.456203282,"remaining_time":8.116441698},
{"learn":[0.007094572527],"iteration":201,"passed_time":5.486937321,"remaining_time":8.094590701},
{"learn":[0.007078293118],"iteration":202,"passed_time":5.521182573,"remaining_time":8.077789282},
{"learn":[0.007062629451],"iteration":203,"passed_time":5.555129696,"remaining_time":8.060384265},
{"learn":[0.007057319587],"iteration":204,"passed_time":5.583489312,"remaining_time":8.034777302},
{"learn":[0.007052880438],"iteration":205,"passed_time":5.616304598,"remaining_time":8.015502679},
{"learn":[0.007048670747],"iteration":206,"passed_time":5.646519712,"remaining_time":7.992416791},
{"learn":[0.007043013716],"iteration":207,"passed_time":5.67851861,"remaining_time":7.971766511},
{"learn":[0.007034223036],"iteration":208,"passed_time":5.708708696,"remaining_time":7.948489142},
{"learn":[0.007023223344],"iteration":209,"passed_time":5.739788212,"remaining_time":7.926374198},
{"learn":[0.007005773113],"iteration":210,"passed_time":5.767894901,"remaining_time":7.900102495},
{"learn":[0.007001360443],"iteration":211,"passed_time":5.795282882,"remaining_time":7.872837122},
{"learn":[0.006995918428],"iteration":212,"passed_time":5.827819137,"remaining_time":7.852507476},
{"learn":[0.006992228796],"iteration":213,"passed_time":5.858188744,"remaining_time":7.829168135},
{"learn":[0.006985513053],"iteration":214,"passed_time":5.884665508,"remaining_time":7.800603115},
{"learn":[0.006973774736],"iteration":215,"passed_time":5.909887369,"remaining_time":7.770407467},
{"learn":[0.006969967516],"iteration":216,"passed_time":5.935259955,"remaining_time":7.740454227},
{"learn":[0.006959445095],"iteration":217,"passed_time":5.961413339,"remaining_time":7.711553034},
{"learn":[0.006957124572],"iteration":218,"passed_time":5.986313601,"remaining_time":7.68106905},
{"learn":[0.006951827224],"iteration":219,"passed_time":6.014215057,"remaining_time":7.654455527},
{"learn":[0.006945680405],"iteration":220,"passed_time":6.039014916,"remaining_time":7.623914759},
{"learn":[0.006942308512],"iteration":221,"passed_time":6.064732461,"remaining_time":7.594574883},
{"learn":[0.006925100921],"iteration":222,"passed_time":6.090260629,"remaining_time":7.565032261},
{"learn":[0.006906751089],"iteration":223,"passed_time":6.116313748,"remaining_time":7.536172297},
{"learn":[0.006893489848],"iteration":224,"passed_time":6.142785633,"remaining_time":7.507849107},
{"learn":[0.006888570058],"iteration":225,"passed_time":6.169358937,"remaining_time":7.479665259},
{"learn":[0.006878176297],"iteration":226,"passed_time":6.197546992,"remaining_time":7.453437572},
{"learn":[0.006873635808],"iteration":227,"passed_time":6.224773651,"remaining_time":7.42604576},
{"learn":[0.006870921661],"iteration":228,"passed_time":6.249216701,"remaining_time":7.395361249},
{"learn":[0.006860423131],"iteration":229,"passed_time":6.27422807,"remaining_time":7.365398169},
{"learn":[0.006847382623],"iteration":230,"passed_time":6.301104937,"remaining_time":7.337650338},
{"learn":[0.00684251639],"iteration":231,"passed_time":6.326875382,"remaining_time":7.308631907},
{"learn":[0.006837056743],"iteration":232,"passed_time":6.353133496,"remaining_time":7.280200187},
{"learn":[0.006829246364],"iteration":233,"passed_time":6.378053069,"remaining_time":7.250265455},
{"learn":[0.006816982753],"iteration":234,"passed_time":6.403416554,"remaining_time":7.220873986},
{"learn":[0.006813166687],"iteration":235,"passed_time":6.429998062,"remaining_time":7.192879188},
{"learn":[0.006801565455],"iteration":236,"passed_time":6.455934723,"remaining_time":7.164180726},
{"learn":[0.006792185635],"iteration":237,"passed_time":6.482186188,"remaining_time":7.135852022},
{"learn":[0.006789264235],"iteration":238,"passed_time":6.509599198,"remaining_time":7.108809165},
{"learn":[0.00677754078],"iteration":239,"passed_time":6.536273893,"remaining_time":7.080963385},
{"learn":[0.006771399858],"iteration":240,"passed_time":6.563290649,"remaining_time":7.053494929},
{"learn":[0.00676099322],"iteration":241,"passed_time":6.590014006,"remaining_time":7.025717411},
{"learn":[0.006757292093],"iteration":242,"passed_time":6.615029883,"remaining_time":6.996142716},
{"learn":[0.006745244883],"iteration":243,"passed_time":6.641627103,"remaining_time":6.968264501},
{"learn":[0.006734880489],"iteration":244,"passed_time":6.665978588,"remaining_time":6.938059347},
{"learn":[0.006726968408],"iteration":245,"passed_time":6.693954735,"remaining_time":6.911644319},
{"learn":[0.006718436375],"iteration":246,"passed_time":6.719584059,"remaining_time":6.882812821},
{"learn":[0.006714399755],"iteration":247,"passed_time":6.745373852,"remaining_time":6.854170205},
{"learn":[0.006708117536],"iteration":248,"passed_time":6.769865177,"remaining_time":6.824241604},
{"learn":[0.006704265302],"iteration":249,"passed_time":6.796296631,"remaining_time":6.796296631},
{"learn":[0.006699896983],"iteration":250,"passed_time":6.825308457,"remaining_time":6.770923529},
{"learn":[0.006690363286],"iteration":251,"passed_time":6.853585097,"remaining_time":6.744798032},
{"learn":[0.006684700719],"iteration":252,"passed_time":6.879223798,"remaining_time":6.716080151},
{"learn":[0.006682070219],"iteration":253,"passed_time":6.904309784,"remaining_time":6.686851208},
{"learn":[0.006671354807],"iteration":254,"passed_time":6.932461234,"remaining_time":6.660600009},
{"learn":[0.006668912183],"iteration":255,"passed_time":6.958100915,"remaining_time":6.631939935},
{"learn":[0.006665353258],"iteration":256,"passed_time":6.987168593,"remaining_time":6.606544623},
{"learn":[0.006656270655],"iteration":257,"passed_time":7.015102243,"remaining_time":6.580057142},
{"learn":[0.0066514578],"iteration":258,"passed_time":7.045314482,"remaining_time":6.555678727},
{"learn":[0.006642730187],"iteration":259,"passed_time":7.076161173,"remaining_time":6.531841083},
{"learn":[0.006639305218],"iteration":260,"passed_time":7.105331821,"remaining_time":6.506414962},
{"learn":[0.006628877096],"iteration":261,"passed_time":7.137933398,"remaining_time":6.484076903},
{"learn":[0.006625516517],"iteration":262,"passed_time":7.168080746,"remaining_time":6.459449189},
{"learn":[0.006617706258],"iteration":263,"passed_time":7.201661642,"remaining_time":6.437849044},
{"learn":[0.006608968114],"iteration":264,"passed_time":7.229391475,"remaining_time":6.410969798},
{"learn":[0.006602046022],"iteration":265,"passed_time":7.257369851,"remaining_time":6.384302801},
{"learn":[0.006599831773],"iteration":266,"passed_time":7.281537659,"remaining_time":6.354300653},
{"learn":[0.006597721271],"iteration":267,"passed_time":7.306828406,"remaining_time":6.325314143},
{"learn":[0.006595772408],"iteration":268,"passed_time":7.331799856,"remaining_time":6.296080917},
{"learn":[0.00659259176],"iteration":269,"passed_time":7.358150262,"remaining_time":6.268053927},
{"learn":[0.006586950616],"iteration":270,"passed_time":7.387237695,"remaining_time":6.242352149},
{"learn":[0.006584054009],"iteration":271,"passed_time":7.410850521,"remaining_time":6.212036466},
{"learn":[0.006578558736],"iteration":272,"passed_time":7.436342962,"remaining_time":6.183332793},
{"learn":[0.006567517943],"iteration":273,"passed_time":7.462489179,"remaining_time":6.155191804},
{"learn":[0.006560602591],"iteration":274,"passed_time":7.495487168,"remaining_time":6.132671319},
{"learn":[0.006554118413],"iteration":275,"passed_time":7.526490929,"remaining_time":6.108456406},
{"learn":[0.006548373763],"iteration":276,"passed_time":7.559676287,"remaining_time":6.08594878},
{"learn":[0.00654157979],"iteration":277,"passed_time":7.590710147,"remaining_time":6.061646232},
{"learn":[0.006535402701],"iteration":278,"passed_time":7.619110157,"remaining_time":6.035209121},
{"learn":[0.006533611323],"iteration":279,"passed_time":7.650023174,"remaining_time":6.010732494},
{"learn":[0.006529946243],"iteration":280,"passed_time":7.680884213,"remaining_time":5.986169547},
{"learn":[0.00652408593],"iteration":281,"passed_time":7.708009496,"remaining_time":5.958674008},
{"learn":[0.006517916965],"iteration":282,"passed_time":7.736931123,"remaining_time":5.932558493},
{"learn":[0.006510452789],"iteration":283,"passed_time":7.765337679,"remaining_time":5.906031474},
{"learn":[0.006504218651],"iteration":284,"passed_time":7.791203485,"remaining_time":5.877574559},
{"learn":[0.006502594929],"iteration":285,"passed_time":7.81649847,"remaining_time":5.848708645},
{"learn":[0.006500848384],"iteration":286,"passed_time":7.842063167,"remaining_time":5.820067786},
{"learn":[0.006493096015],"iteration":287,"passed_time":7.869309971,"remaining_time":5.792686507},
{"learn":[0.006489383515],"iteration":288,"passed_time":7.897600764,"remaining_time":5.766068378},
{"learn":[0.006481218025],"iteration":289,"passed_time":7.926592835,"remaining_time":5.739946536},
{"learn":[0.006479564815],"iteration":290,"passed_time":7.952410982,"remaining_time":5.711525413},
{"learn":[0.006477205598],"iteration":291,"passed_time":7.978983376,"remaining_time":5.683659391},
{"learn":[0.006475531266],"iteration":292,"passed_time":8.003669281,"remaining_time":5.654469424},
{"learn":[0.006472612514],"iteration":293,"passed_time":8.029236051,"remaining_time":5.625927301},
{"learn":[0.00646682592],"iteration":294,"passed_time":8.058587442,"remaining_time":5.600035341},
{"learn":[0.006457608458],"iteration":295,"passed_time":8.085200733,"remaining_time":5.572232937},
{"learn":[0.006453789383],"iteration":296,"passed_time":8.111483244,"remaining_time":5.544212453},
{"learn":[0.006449861205],"iteration":297,"passed_time":8.138333859,"remaining_time":5.516588723},
{"learn":[0.006448704705],"iteration":298,"passed_time":8.163748458,"remaining_time":5.488004817},
{"learn":[0.006443440757],"iteration":299,"passed_time":8.194780436,"remaining_time":5.463186958},
{"learn":[0.006441966456],"iteration":300,"passed_time":8.220624057,"remaining_time":5.434897632},
{"learn":[0.006432389131],"iteration":301,"passed_time":8.248105464,"remaining_time":5.407698285},
{"learn":[0.006426881342],"iteration":302,"passed_time":8.274302752,"remaining_time":5.379662185},
{"learn":[0.006419362525],"iteration":303,"passed_time":8.301306286,"remaining_time":5.352158},
{"learn":[0.006412026648],"iteration":304,"passed_time":8.331970904,"remaining_time":5.326997791},
{"learn":[0.006408729857],"iteration":305,"passed_time":8.362892087,"remaining_time":5.301964264},
{"learn":[0.006407353587],"iteration":306,"passed_time":8.391815749,"remaining_time":5.275636611},
{"learn":[0.006401627652],"iteration":307,"passed_time":8.422496829,"remaining_time":5.250387633},
{"learn":[0.006398626516],"iteration":308,"passed_time":8.453627913,"remaining_time":5.225381655},
{"learn":[0.006395844488],"iteration":309,"passed_time":8.483092417,"remaining_time":5.199314707},
{"learn":[0.006392564427],"iteration":310,"passed_time":8.512361059,"remaining_time":5.173106882},
{"learn":[0.006388110955],"iteration":311,"passed_time":8.545234426,"remaining_time":5.149051513},
{"learn":[0.006385257797],"iteration":312,"passed_time":8.575380413,"remaining_time":5.123310343},
{"learn":[0.006378222931],"iteration":313,"passed_time":8.606210356,"remaining_time":5.097946262},
{"learn":[0.006376635256],"iteration":314,"passed_time":8.636380127,"remaining_time":5.072159757},
{"learn":[0.006374709861],"iteration":315,"passed_time":8.665771516,"remaining_time":5.045892275},
{"learn":[0.006368003025],"iteration":316,"passed_time":8.691474663,"remaining_time":5.017475909},
{"learn":[0.006364837904],"iteration":317,"passed_time":8.719340675,"remaining_time":4.990314474},
{"learn":[0.006360012434],"iteration":318,"passed_time":8.744511228,"remaining_time":4.961619223},
{"learn":[0.006356559301],"iteration":319,"passed_time":8.770737665,"remaining_time":4.933539937},
{"learn":[0.006349594159],"iteration":320,"passed_time":8.79738409,"remaining_time":4.905706393},
{"learn":[0.006348078336],"iteration":321,"passed_time":8.825640792,"remaining_time":4.878770376},
{"learn":[0.006345709972],"iteration":322,"passed_time":8.850670033,"remaining_time":4.850057572},
{"learn":[0.00634420829],"iteration":323,"passed_time":8.877080646,"remaining_time":4.822117882},
{"learn":[0.006338769524],"iteration":324,"passed_time":8.905682095,"remaining_time":4.795367282},
{"learn":[0.006332425983],"iteration":325,"passed_time":8.933322761,"remaining_time":4.768092517},
{"learn":[0.006331153219],"iteration":326,"passed_time":8.957195493,"remaining_time":4.73882208},
{"learn":[0.006329871969],"iteration":327,"passed_time":8.983423663,"remaining_time":4.710819726},
{"learn":[0.006324162764],"iteration":328,"passed_time":9.011340696,"remaining_time":4.683705954},
{"learn":[0.006318027017],"iteration":329,"passed_time":9.03760124,"remaining_time":4.655733972},
{"learn":[0.006313303729],"iteration":330,"passed_time":9.06522426,"remaining_time":4.628467976},
{"learn":[0.006309064973],"iteration":331,"passed_time":9.090271819,"remaining_time":4.599896583},
{"learn":[0.006304430606],"iteration":332,"passed_time":9.116529481,"remaining_time":4.571953223},
{"learn":[0.006302317074],"iteration":333,"passed_time":9.143039098,"remaining_time":4.54414518},
{"learn":[0.006297612841],"iteration":334,"passed_time":9.170603118,"remaining_time":4.516864222},
{"learn":[0.006296386955],"iteration":335,"passed_time":9.196962265,"remaining_time":4.488993486},
{"learn":[0.006294909065],"iteration":336,"passed_time":9.223766066,"remaining_time":4.461346791},
{"learn":[0.00628896324],"iteration":337,"passed_time":9.249459275,"remaining_time":4.433172788},
{"learn":[0.006280779817],"iteration":338,"passed_time":9.276377398,"remaining_time":4.405595165},
{"learn":[0.006278146549],"iteration":339,"passed_time":9.303307978,"remaining_time":4.378027284},
{"learn":[0.006272546506],"iteration":340,"passed_time":9.331889451,"remaining_time":4.351232911},
{"learn":[0.006266396979],"iteration":341,"passed_time":9.357648108,"remaining_time":4.32312398},
{"learn":[0.006260870293],"iteration":342,"passed_time":9.384204924,"remaining_time":4.295394091},
{"learn":[0.006255715929],"iteration":343,"passed_time":9.410960955,"remaining_time":4.267761363},
{"learn":[0.006254557864],"iteration":344,"passed_time":9.435511906,"remaining_time":4.23914303},
{"learn":[0.006252669118],"iteration":345,"passed_time":9.46194882,"remaining_time":4.211387625},
{"learn":[0.006247169392],"iteration":346,"passed_time":9.494030355,"remaining_time":4.186128658},
{"learn":[0.006246080411],"iteration":347,"passed_time":9.52344696,"remaining_time":4.159666488},
{"learn":[0.006243888067],"iteration":348,"passed_time":9.554328629,"remaining_time":4.133821269},
{"learn":[0.006241298609],"iteration":349,"passed_time":9.581642704,"remaining_time":4.106418302},
{"learn":[0.006239449821],"iteration":350,"passed_time":9.60896962,"remaining_time":4.079021291},
{"learn":[0.006231872029],"iteration":351,"passed_time":9.635591339,"remaining_time":4.051328177},
{"learn":[0.006230115494],"iteration":352,"passed_time":9.661017428,"remaining_time":4.023143235},
{"learn":[0.00622488362],"iteration":353,"passed_time":9.688190579,"remaining_time":3.99569442},
{"learn":[0.006223600204],"iteration":354,"passed_time":9.713344579,"remaining_time":3.967422434},
{"learn":[0.006221132126],"iteration":355,"passed_time":9.73880528,"remaining_time":3.939292023},
{"learn":[0.006216159919],"iteration":356,"passed_time":9.766632132,"remaining_time":3.912124355},
{"learn":[0.006215232516],"iteration":357,"passed_time":9.793346472,"remaining_time":3.884511729},
{"learn":[0.006204568558],"iteration":358,"passed_time":9.818570072,"remaining_time":3.856318608},
{"learn":[0.006200348397],"iteration":359,"passed_time":9.848823471,"remaining_time":3.830098016},
{"learn":[0.006195685747],"iteration":360,"passed_time":9.878372207,"remaining_time":3.803583758},
{"learn":[0.006194626434],"iteration":361,"passed_time":9.905944442,"remaining_time":3.776299262},
{"learn":[0.006193649865],"iteration":362,"passed_time":9.930642921,"remaining_time":3.747928596},
{"learn":[0.006191344688],"iteration":363,"passed_time":9.955799749,"remaining_time":3.719749357},
{"learn":[0.006185579998],"iteration":364,"passed_time":9.982846369,"remaining_time":3.692285643},
{"learn":[0.006180978067],"iteration":365,"passed_time":10.00897861,"remaining_time":3.664489438},
{"learn":[0.006175165296],"iteration":366,"passed_time":10.03606148,"remaining_time":3.637046803},
{"learn":[0.006172066671],"iteration":367,"passed_time":10.06395951,"remaining_time":3.609898519},
{"learn":[0.006168420969],"iteration":368,"passed_time":10.08895882,"remaining_time":3.581717087},
{"learn":[0.006165608491],"iteration":369,"passed_time":10.11569904,"remaining_time":3.554164528},
{"learn":[0.006163405375],"iteration":370,"passed_time":10.14328364,"remaining_time":3.526909945},
{"learn":[0.006158240419],"iteration":371,"passed_time":10.17240127,"remaining_time":3.500181081},
{"learn":[0.006156072929],"iteration":372,"passed_time":10.20046869,"remaining_time":3.473081834},
{"learn":[0.006151636007],"iteration":373,"passed_time":10.22639712,"remaining_time":3.445256784},
{"learn":[0.006150704151],"iteration":374,"passed_time":10.25173901,"remaining_time":3.417246336},
{"learn":[0.006144672088],"iteration":375,"passed_time":10.27856038,"remaining_time":3.389737997},
{"learn":[0.006140367196],"iteration":376,"passed_time":10.30682617,"remaining_time":3.36270456},
{"learn":[0.006138354905],"iteration":377,"passed_time":10.33145726,"remaining_time":3.334491495},
{"learn":[0.006136750921],"iteration":378,"passed_time":10.36018688,"remaining_time":3.307605837},
{"learn":[0.006134645172],"iteration":379,"passed_time":10.38450536,"remaining_time":3.279317482},
{"learn":[0.006131667566],"iteration":380,"passed_time":10.41252192,"remaining_time":3.252205009},
{"learn":[0.006130880137],"iteration":381,"passed_time":10.44229171,"remaining_time":3.225629376},
{"learn":[0.006130011528],"iteration":382,"passed_time":10.47046537,"remaining_time":3.198549473},
{"learn":[0.006125454911],"iteration":383,"passed_time":10.50086276,"remaining_time":3.172135626},
{"learn":[0.006122258016],"iteration":384,"passed_time":10.53155198,"remaining_time":3.145788253},
{"learn":[0.006119941345],"iteration":385,"passed_time":10.56051854,"remaining_time":3.118909619},
{"learn":[0.006115194265],"iteration":386,"passed_time":10.5925182,"remaining_time":3.092905832},
{"learn":[0.006112157444],"iteration":387,"passed_time":10.61881885,"remaining_time":3.065226061},
{"learn":[0.006108978722],"iteration":388,"passed_time":10.64362901,"remaining_time":3.037128071},
{"learn":[0.00610544808],"iteration":389,"passed_time":10.67005494,"remaining_time":3.009502675},
{"learn":[0.006104366863],"iteration":390,"passed_time":10.69567241,"remaining_time":2.981658036},
{"learn":[0.006100887673],"iteration":391,"passed_time":10.7247218,"remaining_time":2.954770292},
{"learn":[0.006096434261],"iteration":392,"passed_time":10.75267582,"remaining_time":2.927573314},
{"learn":[0.006092757146],"iteration":393,"passed_time":10.77818598,"remaining_time":2.899715009},
{"learn":[0.006091885047],"iteration":394,"passed_time":10.80381617,"remaining_time":2.8719005},
{"learn":[0.006083926125],"iteration":395,"passed_time":10.82993823,"remaining_time":2.844226201},
{"learn":[0.006082313897],"iteration":396,"passed_time":10.85321429,"remaining_time":2.81582134},
{"learn":[0.006080316951],"iteration":397,"passed_time":10.88220294,"remaining_time":2.788906282},
{"learn":[0.006076876417],"iteration":398,"passed_time":10.91503425,"remaining_time":2.762953533},
{"learn":[0.006075385387],"iteration":399,"passed_time":10.94707847,"remaining_time":2.736769617},
{"learn":[0.00607272197],"iteration":400,"passed_time":10.97736141,"remaining_time":2.710121646},
{"learn":[0.006070981962],"iteration":401,"passed_time":11.003302,"remaining_time":2.682397004},
{"learn":[0.006068751186],"iteration":402,"passed_time":11.03042416,"remaining_time":2.654965617},
{"learn":[0.006063380219],"iteration":403,"passed_time":11.05897413,"remaining_time":2.627875042},
{"learn":[0.006062602358],"iteration":404,"passed_time":11.0899384,"remaining_time":2.601343575},
{"learn":[0.00605741285],"iteration":405,"passed_time":11.12043401,"remaining_time":2.574681766},
{"learn":[0.006055910085],"iteration":406,"passed_time":11.15004263,"remaining_time":2.547798439},
{"learn":[0.006052783177],"iteration":407,"passed_time":11.17825912,"remaining_time":2.520587841},
{"learn":[0.006050354091],"iteration":408,"passed_time":11.20506012,"remaining_time":2.493057387},
{"learn":[0.006045780324],"iteration":409,"passed_time":11.23310674,"remaining_time":2.465803918},
{"learn":[0.006044001946],"iteration":410,"passed_time":11.25787164,"remaining_time":2.437835952},
{"learn":[0.00604280657],"iteration":411,"passed_time":11.2838268,"remaining_time":2.410137762},
{"learn":[0.006037948461],"iteration":412,"passed_time":11.31056947,"remaining_time":2.382613909},
{"learn":[0.006033780654],"iteration":413,"passed_time":11.33958487,"remaining_time":2.355565939},
{"learn":[0.006032993406],"iteration":414,"passed_time":11.36656856,"remaining_time":2.328092356},
{"learn":[0.006029464569],"iteration":415,"passed_time":11.39180571,"remaining_time":2.30026846},
{"learn":[0.006027949288],"iteration":416,"passed_time":11.42162569,"remaining_time":2.273369142},
{"learn":[0.006025736423],"iteration":417,"passed_time":11.44776867,"remaining_time":2.245734525},
{"learn":[0.006024636249],"iteration":418,"passed_time":11.47844668,"remaining_time":2.218983726},
{"learn":[0.006023206661],"iteration":419,"passed_time":11.50939754,"remaining_time":2.192266197},
{"learn":[0.006021255991],"iteration":420,"passed_time":11.53668692,"remaining_time":2.164841489},
{"learn":[0.00601948736],"iteration":421,"passed_time":11.56975851,"remaining_time":2.13848617},
{"learn":[0.006015756987],"iteration":422,"passed_time":11.60086191,"remaining_time":2.11174082},
{"learn":[0.006012515801],"iteration":423,"passed_time":11.63048253,"remaining_time":2.084709132},
{"learn":[0.006009553059],"iteration":424,"passed_time":11.65531512,"remaining_time":2.056820316},
{"learn":[0.006007209127],"iteration":425,"passed_time":11.68366854,"remaining_time":2.029557446},
{"learn":[0.006002592814],"iteration":426,"passed_time":11.71788646,"remaining_time":2.003292064},
{"learn":[0.005999067347],"iteration":427,"passed_time":11.74304476,"remaining_time":1.975465474},
{"learn":[0.005996291758],"iteration":428,"passed_time":11.77094255,"remaining_time":1.94810471},
{"learn":[0.005995134174],"iteration":429,"passed_time":11.79552744,"remaining_time":1.920202142},
{"learn":[0.005991535712],"iteration":430,"passed_time":11.82154479,"remaining_time":1.892544294},
{"learn":[0.005989957905],"iteration":431,"passed_time":11.85104897,"remaining_time":1.865442894},
{"learn":[0.005988660227],"iteration":432,"passed_time":11.87859258,"remaining_time":1.838027028},
{"learn":[0.005984604171],"iteration":433,"passed_time":11.90298947,"remaining_time":1.810132038},
{"learn":[0.005982551801],"iteration":434,"passed_time":11.92856718,"remaining_time":1.782429579},
{"learn":[0.005978993718],"iteration":435,"passed_time":11.95765974,"remaining_time":1.755252806},
{"learn":[0.00597570463],"iteration":436,"passed_time":11.98532721,"remaining_time":1.727861817},
{"learn":[0.005972686223],"iteration":437,"passed_time":12.01049698,"remaining_time":1.700116011},
{"learn":[0.005968963613],"iteration":438,"passed_time":12.03585857,"remaining_time":1.672408594},
{"learn":[0.005966218174],"iteration":439,"passed_time":12.06294585,"remaining_time":1.644947162},
{"learn":[0.005964626285],"iteration":440,"passed_time":12.09458563,"remaining_time":1.61809649},
{"learn":[0.005960216683],"iteration":441,"passed_time":12.12136562,"remaining_time":1.590586439},
{"learn":[0.005955815927],"iteration":442,"passed_time":12.14934,"remaining_time":1.563233363},
{"learn":[0.005951736702],"iteration":443,"passed_time":12.17780805,"remaining_time":1.535939754},
{"learn":[0.00594978549],"iteration":444,"passed_time":12.20385185,"remaining_time":1.50834124},
{"learn":[0.005948266718],"iteration":445,"passed_time":12.23400618,"remaining_time":1.481247385},
{"learn":[0.005946413899],"iteration":446,"passed_time":12.26013692,"remaining_time":1.453662767},
{"learn":[0.005942786068],"iteration":447,"passed_time":12.28765463,"remaining_time":1.426245627},
{"learn":[0.005940201725],"iteration":448,"passed_time":12.31457511,"remaining_time":1.398760202},
{"learn":[0.005937056824],"iteration":449,"passed_time":12.34308174,"remaining_time":1.371453526},
{"learn":[0.005933491339],"iteration":450,"passed_time":12.36901528,"remaining_time":1.343861971},
{"learn":[0.005932050016],"iteration":451,"passed_time":12.39653005,"remaining_time":1.316445669},
{"learn":[0.00592909961],"iteration":452,"passed_time":12.42224104,"remaining_time":1.288841785},
{"learn":[0.005927612853],"iteration":453,"passed_time":12.44696415,"remaining_time":1.261146147},
{"learn":[0.005923956439],"iteration":454,"passed_time":12.4768935,"remaining_time":1.233978478},
{"learn":[0.005920619329],"iteration":455,"passed_time":12.50277121,"remaining_time":1.206407748},
{"learn":[0.005919068542],"iteration":456,"passed_time":12.52931894,"remaining_time":1.178907471},
{"learn":[0.005917858423],"iteration":457,"passed_time":12.55954397,"remaining_time":1.151748574},
{"learn":[0.005909149224],"iteration":458,"passed_time":12.58338511,"remaining_time":1.124006077},
{"learn":[0.005906229329],"iteration":459,"passed_time":12.61129013,"remaining_time":1.096633924},
{"learn":[0.005903833884],"iteration":460,"passed_time":12.63733879,"remaining_time":1.069102414},
{"learn":[0.005902682258],"iteration":461,"passed_time":12.66365251,"remaining_time":1.041599124},
{"learn":[0.005901115524],"iteration":462,"passed_time":12.69035976,"remaining_time":1.014132421},
{"learn":[0.005897979167],"iteration":463,"passed_time":12.71806435,"remaining_time":0.986746372},
{"learn":[0.005896186465],"iteration":464,"passed_time":12.74817459,"remaining_time":0.9595400227},
{"learn":[0.005893363877],"iteration":465,"passed_time":12.77728026,"remaining_time":0.9322479157},
{"learn":[0.005892263042],"iteration":466,"passed_time":12.807199,"remaining_time":0.9050054971},
{"learn":[0.005891170871],"iteration":467,"passed_time":12.83955888,"remaining_time":0.8779185562},
{"learn":[0.005890130635],"iteration":468,"passed_time":12.86821451,"remaining_time":0.8505642853},
{"learn":[0.005887974638],"iteration":469,"passed_time":12.89765049,"remaining_time":0.8232542866},
{"learn":[0.005886605349],"iteration":470,"passed_time":12.92912414,"remaining_time":0.7960607222},
{"learn":[0.005885315674],"iteration":471,"passed_time":12.96055447,"remaining_time":0.7688464518},
{"learn":[0.005883006886],"iteration":472,"passed_time":12.98584809,"remaining_time":0.7412640557},
{"learn":[0.005878954561],"iteration":473,"passed_time":13.01213386,"remaining_time":0.7137457392},
{"learn":[0.005875276604],"iteration":474,"passed_time":13.03697281,"remaining_time":0.6861564636},
{"learn":[0.005871822507],"iteration":475,"passed_time":13.0635101,"remaining_time":0.6586643746},
{"learn":[0.005869174676],"iteration":476,"passed_time":13.09041398,"remaining_time":0.6311939654},
{"learn":[0.005862296815],"iteration":477,"passed_time":13.117419,"remaining_time":0.6037305816},
{"learn":[0.005860301072],"iteration":478,"passed_time":13.14506134,"remaining_time":0.5762970524},
{"learn":[0.005859317583],"iteration":479,"passed_time":13.17648879,"remaining_time":0.5490203661},
{"learn":[0.005856813518],"iteration":480,"passed_time":13.20563249,"remaining_time":0.5216362106},
{"learn":[0.005854828306],"iteration":481,"passed_time":13.23518145,"remaining_time":0.494259888},
{"learn":[0.005852972538],"iteration":482,"passed_time":13.26513562,"remaining_time":0.4668888315},
{"learn":[0.005850726634],"iteration":483,"passed_time":13.29561128,"remaining_time":0.4395243398},
{"learn":[0.005848552344],"iteration":484,"passed_time":13.32385173,"remaining_time":0.4120778886},
{"learn":[0.005846759281],"iteration":485,"passed_time":13.35290167,"remaining_time":0.3846514885},
{"learn":[0.005845167995],"iteration":486,"passed_time":13.38389178,"remaining_time":0.3572702118},
{"learn":[0.005843474587],"iteration":487,"passed_time":13.41553281,"remaining_time":0.3298901511},
{"learn":[0.005841431965],"iteration":488,"passed_time":13.44381306,"remaining_time":0.3024170628},
{"learn":[0.005839511746],"iteration":489,"passed_time":13.47382347,"remaining_time":0.2749759892},
{"learn":[0.005837872558],"iteration":490,"passed_time":13.50393233,"remaining_time":0.2475262545},
{"learn":[0.005834719531],"iteration":491,"passed_time":13.5386483,"remaining_time":0.2201406228},
{"learn":[0.005832872128],"iteration":492,"passed_time":13.57074198,"remaining_time":0.1926880199},
{"learn":[0.005829429888],"iteration":493,"passed_time":13.59775092,"remaining_time":0.1651548695},
{"learn":[0.00582620164],"iteration":494,"passed_time":13.62396215,"remaining_time":0.1376157793},
{"learn":[0.005823766056],"iteration":495,"passed_time":13.64959185,"remaining_time":0.1100773536},
{"learn":[0.005822770592],"iteration":496,"passed_time":13.67897713,"remaining_time":0.08256927843},
{"learn":[0.005821215593],"iteration":497,"passed_time":13.7045978,"remaining_time":0.05503854538},
{"learn":[0.005818894709],"iteration":498,"passed_time":13.73014602,"remaining_time":0.02751532269},
{"learn":[0.005811415608],"iteration":499,"passed_time":13.75713167,"remaining_time":0}
]}